README.md
setup.py
islam_sdk/__init__.py
islam_sdk.egg-info/PKG-INFO
islam_sdk.egg-info/SOURCES.txt
islam_sdk.egg-info/dependency_links.txt
islam_sdk.egg-info/top_level.txt