Metadata-Version: 2.4
Name: islam-sdk
Version: 0.0.1
Summary: Official Python SDK for Islamic APIs
Author: Mohammed Raad
Author-email: you@example.com
License: MIT
Keywords: islam quran sdk prayer hadith
Dynamic: author
Dynamic: author-email
Dynamic: keywords
Dynamic: license
Dynamic: summary
